nodejs_eval/__about__.py
nodejs_eval/__init__.py
nodejs_eval/eval.py
nodejs_eval-0.0.5.dist-info/METADATA
nodejs_eval-0.0.5.dist-info/WHEEL
nodejs_eval-0.0.5.dist-info/licenses/LICENSE.txt
nodejs_eval-0.0.5.dist-info/RECORD
