Metadata-Version: 2.1
Name: nodejs-eval
Version: 0.0.5
Summary: Evaluate arbitrary JavaScript from Python using a NodeJS sidecar
Project-URL: Documentation, https://github.com/bpcreech/nodejs-eval#readme
Project-URL: Issues, https://github.com/bpcreech/nodejs-eval/issues
Project-URL: Source, https://github.com/bpcreech/nodejs-eval
Author-email: Ben Creech <ben@bpcreech.com>
License-Expression: MIT
License-File: LICENSE.txt
Classifier: Development Status :: 4 - Beta
Classifier: Programming Language :: Python
Classifier: Programming Language :: Python :: 3.8
Classifier: Programming Language :: Python :: 3.9
Classifier: Programming Language :: Python :: 3.10
Classifier: Programming Language :: Python :: 3.11
Classifier: Programming Language :: Python :: 3.12
Classifier: Programming Language :: Python :: Implementation :: CPython
Classifier: Programming Language :: Python :: Implementation :: PyPy
Requires-Python: >=3.8
Requires-Dist: aiohttp
Requires-Dist: nodejs-bin
